{
	"id": "9yfXBPtLAz3gzZ7",
	"json": "{\"id\":\"9yfXBPtLAz3gzZ7\",\"url\":\"https://noah-garden.com/noah\",\"loadedUrl\":\"https://noah-garden.com/noah\",\"uniqueKey\":\"https://noah-garden.com/noah\",\"method\":\"GET\",\"noRetry\":false,\"retryCount\":0,\"errorMessages\":[],\"headers\":{},\"userData\":{\"__crawlee\":{\"state\":4}},\"handledAt\":\"2025-09-25T07:43:03.623Z\"}",
	"method": "GET",
	"orderNo": null,
	"retryCount": 0,
	"uniqueKey": "https://noah-garden.com/noah",
	"url": "https://noah-garden.com/noah"
}